osxphotos/__init__.py
osxphotos/__main__.py
osxphotos/_constants.py
osxphotos/_version.py
osxphotos/adjustmentsinfo.py
osxphotos/albuminfo.py
osxphotos/bookmark.py
osxphotos/commentinfo.py
osxphotos/compare_exif.py
osxphotos/compare_libraries.py
osxphotos/configoptions.py
osxphotos/crash_reporter.py
osxphotos/datetime_formatter.py
osxphotos/datetime_utils.py
osxphotos/debug.py
osxphotos/dictdiff.py
osxphotos/disclaim.py
osxphotos/exif_datetime_updater.py
osxphotos/exif_orientation.py
osxphotos/exifinfo.py
osxphotos/exiftool.py
osxphotos/exiftool_filetypes.json
osxphotos/exifutils.py
osxphotos/exifwriter.py
osxphotos/export_db.py
osxphotos/export_db_utils.py
osxphotos/exportoptions.py
osxphotos/fileutil.py
osxphotos/fingerprint.py
osxphotos/fingerprintquery.py
osxphotos/frozen_photoinfo.py
osxphotos/gitignorefile.py
osxphotos/image_file_utils.py
osxphotos/imageconverter.py
osxphotos/iphoto.py
osxphotos/markdown_utils.py
osxphotos/media_analysis.py
osxphotos/metadata_reader.py
osxphotos/momentinfo.py
osxphotos/path_utils.py
osxphotos/personinfo.py
osxphotos/photo_signature.py
osxphotos/photodates.py
osxphotos/photoexporter.py
osxphotos/photoinfo.py
osxphotos/photoinfo_common.py
osxphotos/photoinfo_dict.py
osxphotos/photoinfo_file.py
osxphotos/photoinfo_protocol.py
osxphotos/photokit.py
osxphotos/photokit_utils.py
osxphotos/photoquery.py
osxphotos/photos_datetime.py
osxphotos/photos_selection.py
osxphotos/photosalbum.py
osxphotos/photoscript_utils.py
osxphotos/phototables.py
osxphotos/phototemplate.cog.md
osxphotos/phototemplate.md
osxphotos/phototemplate.py
osxphotos/phototemplate.tx
osxphotos/phototz.py
osxphotos/placeinfo.py
osxphotos/platform.py
osxphotos/pyrepl.py
osxphotos/query_builder.py
osxphotos/rehydrate.py
osxphotos/rich_utils.py
osxphotos/scoreinfo.py
osxphotos/searchinfo.py
osxphotos/shareinfo.py
osxphotos/shareparticipant.py
osxphotos/sidecars.py
osxphotos/sqlgrep.py
osxphotos/sqlite3_datetime.py
osxphotos/sqlite_utils.py
osxphotos/sqlitekvstore.py
osxphotos-0.75.0.dist-info/licenses/LICENSE
osxphotos-0.75.0.dist-info/METADATA
osxphotos-0.75.0.dist-info/WHEEL
osxphotos-0.75.0.dist-info/entry_points.txt
osxphotos-0.75.0.dist-info/top_level.txt
osxphotos-0.75.0.dist-info/RECORD
