Metadata-Version: 2.4
Name: osxphotos
Version: 0.75.0
Summary: Export photos from Apple's macOS Photos app and query the Photos library database to access metadata about images.
Home-page: https://github.com/RhetTbull/
Download-URL: https://github.com/RhetTbull/osxphotos
Author: Rhet Turnbull
Author-email: rturnbull+git@gmail.com
License: License :: OSI Approved :: MIT License
Project-URL: GitHub, https://github.com/RhetTbull/osxphotos
Classifier: Development Status :: 4 - Beta
Classifier: Environment :: MacOS X
Classifier: Intended Audience :: Developers
Classifier: License :: OSI Approved :: MIT License
Classifier: Operating System :: MacOS :: MacOS X
Classifier: Programming Language :: Python :: 3.10
Classifier: Programming Language :: Python :: 3.11
Classifier: Programming Language :: Python :: 3.12
Classifier: Programming Language :: Python :: 3.13
Classifier: Programming Language :: Python :: 3.14
Classifier: Topic :: Software Development :: Libraries :: Python Modules
Requires-Python: >=3.10
License-File: LICENSE
Requires-Dist: beautifulsoup4
Requires-Dist: bitmath<1.4.0.0,>=1.3.3.1
Requires-Dist: bpylist2<5.0.0,>=4.1.1
Requires-Dist: cgmetadata>=0.2.0; sys_platform == "darwin"
Requires-Dist: Click<9.0,>=8.1.3
Requires-Dist: mac-alias<3.0.0,>=2.2.2; sys_platform == "darwin"
Requires-Dist: makelive>=0.6.2; sys_platform == "darwin"
Requires-Dist: Mako<1.3.0,>=1.2.2
Requires-Dist: markdown2
Requires-Dist: more-itertools<9.0.0,>=8.8.0
Requires-Dist: objexplore<2.0.0,>=1.6.3
Requires-Dist: osxmetadata<2.0.0,>=1.4.0; sys_platform == "darwin"
Requires-Dist: packaging>=21.3
Requires-Dist: pathvalidate<4.0.0,>=2.4.1
Requires-Dist: photoscript>=0.5.3; sys_platform == "darwin"
Requires-Dist: pip
Requires-Dist: psutil
Requires-Dist: ptpython<4.0.0,>=3.0.20
Requires-Dist: pyobjc-core>=9.0; sys_platform == "darwin" and platform_release >= "22.0"
Requires-Dist: pyobjc-framework-AppleScriptKit>=9.0; sys_platform == "darwin" and platform_release >= "22.0"
Requires-Dist: pyobjc-framework-AppleScriptObjC>=9.0; sys_platform == "darwin" and platform_release >= "22.0"
Requires-Dist: pyobjc-framework-AVFoundation>=9.0; sys_platform == "darwin" and platform_release >= "22.0"
Requires-Dist: pyobjc-framework-Cocoa>=9.0; sys_platform == "darwin" and platform_release >= "22.0"
Requires-Dist: pyobjc-framework-CoreServices>=9.0; sys_platform == "darwin" and platform_release >= "22.0"
Requires-Dist: pyobjc-framework-Metal>=9.0; sys_platform == "darwin" and platform_release >= "22.0"
Requires-Dist: pyobjc-framework-Photos>=9.0; sys_platform == "darwin" and platform_release >= "22.0"
Requires-Dist: pyobjc-framework-Quartz>=9.0; sys_platform == "darwin" and platform_release >= "22.0"
Requires-Dist: pyobjc-framework-Vision>=9.0; sys_platform == "darwin" and platform_release >= "22.0"
Requires-Dist: pyobjc-core<10.0,>=9.0; sys_platform == "darwin" and platform_release < "22.0"
Requires-Dist: pyobjc-framework-AppleScriptKit<10.0,>=9.0; sys_platform == "darwin" and platform_release < "22.0"
Requires-Dist: pyobjc-framework-AppleScriptObjC<10.0,>=9.0; sys_platform == "darwin" and platform_release < "22.0"
Requires-Dist: pyobjc-framework-AVFoundation<10.0,>=9.0; sys_platform == "darwin" and platform_release < "22.0"
Requires-Dist: pyobjc-framework-Cocoa<10.0,>=9.0; sys_platform == "darwin" and platform_release < "22.0"
Requires-Dist: pyobjc-framework-CoreServices<10.0,>=9.0; sys_platform == "darwin" and platform_release < "22.0"
Requires-Dist: pyobjc-framework-Metal<10.0,>=9.0; sys_platform == "darwin" and platform_release < "22.0"
Requires-Dist: pyobjc-framework-Photos<10.0,>=9.0; sys_platform == "darwin" and platform_release < "22.0"
Requires-Dist: pyobjc-framework-Quartz<10.0,>=9.0; sys_platform == "darwin" and platform_release < "22.0"
Requires-Dist: pyobjc-framework-Vision<10.0,>=9.0; sys_platform == "darwin" and platform_release < "22.0"
Requires-Dist: pytimeparse2<2.0.0,>=1.4.0
Requires-Dist: PyYAML<7.0.0,>=6.0.0
Requires-Dist: requests<3.0.0,>=2.27.1
Requires-Dist: rich_theme_manager>=0.11.0
Requires-Dist: rich<14.0.0,>=13.5.2
Requires-Dist: shortuuid<2.0.0,>=1.0.9
Requires-Dist: strpdatetime>=0.4.0
Requires-Dist: tenacity<9.0.0,>=8.0.1
Requires-Dist: textx<5.0.0,>=4.0.1
Requires-Dist: toml<0.11.0,>=0.10.2
Requires-Dist: tzdata
Requires-Dist: utitools>=0.3.0
Requires-Dist: whenever<0.9.0,>=0.8.3
Requires-Dist: wrapt<2.0.0,>=1.14.1
Requires-Dist: wurlitzer<4.0.0,>=3.0.2
Requires-Dist: xdg==5.1.1; python_version <= "3.9"
Requires-Dist: xdg-base-dirs>=6.0.0; python_version >= "3.10"
Dynamic: author
Dynamic: author-email
Dynamic: classifier
Dynamic: description
Dynamic: description-content-type
Dynamic: download-url
Dynamic: home-page
Dynamic: license
Dynamic: license-file
Dynamic: project-url
Dynamic: requires-dist
Dynamic: requires-python
Dynamic: summary
